sphinx_compendia/__init__.py
sphinx_compendia/domain.py
sphinx_compendia/index.py
sphinx_compendia/markup.py
sphinx_compendia/py.typed
sphinx_compendia/sphinxapi.py
sphinx_compendia/store.py
sphinx_compendia/i18n/__init__.py
sphinx_compendia-0.4.0.dist-info/licenses/LICENSE
sphinx_compendia-0.4.0.dist-info/METADATA
sphinx_compendia-0.4.0.dist-info/WHEEL
sphinx_compendia-0.4.0.dist-info/top_level.txt
sphinx_compendia-0.4.0.dist-info/RECORD
