Metadata-Version: 2.4
Name: sphinx-compendia
Version: 0.4.0
Summary: A simple API for creating Sphinx domains and structuring arbitrary collections.
Author-email: Charles Bouchard-Légaré <charlesbouchardlegare@gmail.com>
License-Expression: BSD-2-Clause-Patent
Project-URL: Homepage, https://cblegare.gitlab.io/sphinx-compendia/
Project-URL: Documentation, https://cblegare.gitlab.io/sphinx-compendia/
Project-URL: Repository, https://gitlab.com/cblegare/sphinx-compendia
Project-URL: Issues, https://gitlab.com/cblegare/sphinx-compendia/-/issues
Project-URL: Changelog, https://cblegare.gitlab.io/sphinx-compendia/changelog.html
Keywords: sphinx
Classifier: Development Status :: 4 - Beta
Classifier: Intended Audience :: Developers
Classifier: Intended Audience :: Information Technology
Classifier: Topic :: Documentation
Classifier: Topic :: Documentation :: Sphinx
Classifier: Framework :: Sphinx
Classifier: Programming Language :: Python :: 3
Classifier: Programming Language :: Python :: 3.11
Classifier: Programming Language :: Python :: 3.12
Classifier: Programming Language :: Python :: 3.13
Classifier: Operating System :: OS Independent
Classifier: Typing :: Typed
Requires-Python: >=3.10
License-File: LICENSE
Requires-Dist: docutils>=0.21.2
Requires-Dist: sphinx>=5
Dynamic: license-file
